{
  "abstractgps": {
    "__category__": "External libraries",
    "EnzymeForward": "error",
    "EnzymeReverse": "wrong",
    "FiniteDifferences": 96.35337840229356,
    "ForwardDiff": 2.1693593849327724,
    "MooncakeForward": 21.8591984302896,
    "MooncakeReverse": 7.035540671923949,
    "ReverseDiff": 64.13187372708757,
    "ReverseDiffCompiled": 8.361364624076488,
    "Zygote": 643.3891225631835
  },
  "assume_beta": {
    "__category__": "Distributions",
    "EnzymeForward": 3.033592827760431,
    "EnzymeReverse": 1.9266532860166798,
    "FiniteDifferences": 54.415040650406496,
    "ForwardDiff": 2.0960849594623756,
    "MooncakeForward": 3.8507020174482007,
    "MooncakeReverse": 3.2885982684562896,
    "ReverseDiff": 64.56116570654015,
    "ReverseDiffCompiled": 4.833925823083137,
    "Zygote": 2022.9326924715785
  },
  "control_flow": {
    "__category__": "Base Julia features",
    "EnzymeForward": 4.20091236918551,
    "EnzymeReverse": 2.8172758640035904,
    "FiniteDifferences": 90.36700872242176,
    "ForwardDiff": 2.692619737514914,
    "MooncakeForward": 9.293857487381556,
    "MooncakeReverse": 5.111020876575714,
    "ReverseDiff": 78.7302517434938,
    "ReverseDiffCompiled": "wrong",
    "Zygote": 6060.902108484952
  },
  "delaydiffeq": {
    "__category__": "External libraries",
    "EnzymeForward": "error",
    "EnzymeReverse": "error",
    "FiniteDifferences": 62.303185837892855,
    "ForwardDiff": "wrong",
    "MooncakeForward": "error",
    "MooncakeReverse": "wrong",
    "ReverseDiff": "error",
    "ReverseDiffCompiled": "error",
    "Zygote": "error"
  },
  "demo_assume_dot_observe": {
    "__category__": "DynamicPPL demo models",
    "EnzymeForward": 4.297949529935676,
    "EnzymeReverse": 2.702024726571523,
    "FiniteDifferences": 97.84472749624369,
    "ForwardDiff": 2.923354626403407,
    "MooncakeForward": 7.806140266634072,
    "MooncakeReverse": 5.949855718956411,
    "ReverseDiff": 198.63694487644716,
    "ReverseDiffCompiled": 16.284423305588586,
    "Zygote": "error"
  },
  "demo_assume_dot_observe_literal": {
    "__category__": "DynamicPPL demo models",
    "EnzymeForward": 3.252744663747691,
    "EnzymeReverse": 2.0734838357659253,
    "FiniteDifferences": 76.83512262047677,
    "ForwardDiff": 2.2826990462987307,
    "MooncakeForward": 7.50120912627484,
    "MooncakeReverse": 5.390847718338746,
    "ReverseDiff": 141.31054326231418,
    "ReverseDiffCompiled": 12.14599764787902,
    "Zygote": 6812.747926189267
  },
  "demo_assume_index_observe": {
    "__category__": "DynamicPPL demo models",
    "EnzymeForward": 3.4508878453905676,
    "EnzymeReverse": 19.15390017471138,
    "FiniteDifferences": 92.8927842840952,
    "ForwardDiff": 1.8457531028142398,
    "MooncakeForward": 11.905114576640774,
    "MooncakeReverse": 1.4722680412371134,
    "ReverseDiff": 89.57145316211657,
    "ReverseDiffCompiled": 7.23704733692038,
    "Zygote": "error"
  },
  "demo_assume_matrix_observe_matrix_index": {
    "__category__": "DynamicPPL demo models",
    "EnzymeForward": 4.522157979318054,
    "EnzymeReverse": 13.346995470558628,
    "FiniteDifferences": 81.26307021585794,
    "ForwardDiff": 1.4735716713851617,
    "MooncakeForward": 14.707576927318849,
    "MooncakeReverse": 7.77274543759158,
    "ReverseDiff": 55.57530486745648,
    "ReverseDiffCompiled": 4.859519987298452,
    "Zygote": "error"
  },
  "demo_assume_multivariate_observe": {
    "__category__": "DynamicPPL demo models",
    "EnzymeForward": 4.716210246228374,
    "EnzymeReverse": 9.480840312867723,
    "FiniteDifferences": 87.2547827091112,
    "ForwardDiff": 1.5706627786030145,
    "MooncakeForward": 15.179918623378825,
    "MooncakeReverse": 6.529303929008216,
    "ReverseDiff": 66.04038396001364,
    "ReverseDiffCompiled": 5.741823988799685,
    "Zygote": 3314.7268748621736
  },
  "demo_assume_multivariate_observe_literal": {
    "__category__": "DynamicPPL demo models",
    "EnzymeForward": 4.719500068577698,
    "EnzymeReverse": 8.313441964090691,
    "FiniteDifferences": 85.67029665790463,
    "ForwardDiff": 1.5684099570066377,
    "MooncakeForward": 14.574674623472578,
    "MooncakeReverse": 6.923896459428592,
    "ReverseDiff": 60.648724822987546,
    "ReverseDiffCompiled": 5.554148783342792,
    "Zygote": 2784.431626964014
  },
  "demo_assume_observe_literal": {
    "__category__": "DynamicPPL demo models",
    "EnzymeForward": 4.2424118217276146,
    "EnzymeReverse": 2.6728444806473988,
    "FiniteDifferences": 99.7226366888094,
    "ForwardDiff": 2.063385737452841,
    "MooncakeForward": 8.451384876805438,
    "MooncakeReverse": 5.868379200663808,
    "ReverseDiff": 185.73967253545248,
    "ReverseDiffCompiled": 18.46734234234234,
    "Zygote": 8428.756343437113
  },
  "demo_assume_submodel_observe_index_literal": {
    "__category__": "DynamicPPL demo models",
    "EnzymeForward": 4.205822064948859,
    "EnzymeReverse": 7.697755116493167,
    "FiniteDifferences": 88.87532481893072,
    "ForwardDiff": 1.5380294022714558,
    "MooncakeForward": 13.125565206894645,
    "MooncakeReverse": 5.91776444502413,
    "ReverseDiff": 72.42332039310321,
    "ReverseDiffCompiled": 7.05136180733504,
    "Zygote": "error"
  },
  "assume_dirichlet": {
    "__category__": "Distributions",
    "EnzymeForward": 2.9194249686633555,
    "EnzymeReverse": 3.3640166173907406,
    "FiniteDifferences": 22.7654581410679,
    "ForwardDiff": 1.2238550366327976,
    "MooncakeForward": 3.7794888516383844,
    "MooncakeReverse": 6.002663586328736,
    "ReverseDiff": 50.96107865779106,
    "ReverseDiffCompiled": 4.192860542598762,
    "Zygote": "error"
  },
  "demo_dot_assume_observe": {
    "__category__": "DynamicPPL demo models",
    "EnzymeForward": 4.0645953445488905,
    "EnzymeReverse": 14.789873739206154,
    "FiniteDifferences": 86.01203312489437,
    "ForwardDiff": 1.5255041588864369,
    "MooncakeForward": 14.705952716014638,
    "MooncakeReverse": 6.803069486606027,
    "ReverseDiff": 62.305313942831454,
    "ReverseDiffCompiled": 6.137774100124121,
    "Zygote": "error"
  },
  "demo_dot_assume_observe_index": {
    "__category__": "DynamicPPL demo models",
    "EnzymeForward": 3.918605044862028,
    "EnzymeReverse": 13.685233101820327,
    "FiniteDifferences": 86.51032228262801,
    "ForwardDiff": 1.9379729445892018,
    "MooncakeForward": 12.488074055244875,
    "MooncakeReverse": 5.655219025544168,
    "ReverseDiff": 75.81799897733083,
    "ReverseDiffCompiled": 6.753409804257262,
    "Zygote": "error"
  },
  "demo_dot_assume_observe_index_literal": {
    "__category__": "DynamicPPL demo models",
    "EnzymeForward": 3.9859579479443714,
    "EnzymeReverse": 3.3411657363675396,
    "FiniteDifferences": 90.99660064518366,
    "ForwardDiff": 1.5715998363043542,
    "MooncakeForward": 11.965402346067826,
    "MooncakeReverse": 5.2189499794012635,
    "ReverseDiff": 72.83859407305306,
    "ReverseDiffCompiled": 6.7003913999249365,
    "Zygote": "error"
  },
  "demo_dot_assume_observe_matrix_index": {
    "__category__": "DynamicPPL demo models",
    "EnzymeForward": 4.068339473135469,
    "EnzymeReverse": 13.828357386801805,
    "FiniteDifferences": 82.69848148661767,
    "ForwardDiff": 1.4842816425901553,
    "MooncakeForward": 14.671758072783188,
    "MooncakeReverse": 7.070527934392619,
    "ReverseDiff": 58.24235495855959,
    "ReverseDiffCompiled": 6.849171931022707,
    "Zygote": "error"
  },
  "demo_dot_assume_observe_submodel": {
    "__category__": "DynamicPPL demo models",
    "EnzymeForward": 3.996776306716315,
    "EnzymeReverse": 14.858870725223435,
    "FiniteDifferences": 84.35875395406408,
    "ForwardDiff": 1.4883456689527172,
    "MooncakeForward": 10.162802231866088,
    "MooncakeReverse": 6.377082735911559,
    "ReverseDiff": 62.79179765647327,
    "ReverseDiffCompiled": 5.90460445920085,
    "Zygote": "error"
  },
  "dot_assume": {
    "__category__": "Core Turing syntax",
    "EnzymeForward": 2.7381691448668595,
    "EnzymeReverse": 1.5530749094196,
    "FiniteDifferences": 122.22234384620647,
    "ForwardDiff": 1.6954477184471242,
    "MooncakeForward": 15.726871950193505,
    "MooncakeReverse": 4.3389474099239695,
    "ReverseDiff": 85.94233015044308,
    "ReverseDiffCompiled": 7.432086464230571,
    "Zygote": "error"
  },
  "dot_observe": {
    "__category__": "Core Turing syntax",
    "EnzymeForward": 11.512352575685888,
    "EnzymeReverse": 3.634010466982603,
    "FiniteDifferences": 153.1255973821127,
    "ForwardDiff": 4.261471405218949,
    "MooncakeForward": 8.424592666686873,
    "MooncakeReverse": 13.798560187855317,
    "ReverseDiff": 645.9169132149901,
    "ReverseDiffCompiled": 47.00544968708249,
    "Zygote": "error"
  },
  "dppl_gauss_unknown": {
    "__category__": "DynamicPPL arXiV paper",
    "EnzymeForward": 1.426980565034767,
    "EnzymeReverse": 2.204490767205966,
    "FiniteDifferences": 33.32612569332227,
    "ForwardDiff": 1.5907770804092405,
    "MooncakeForward": 4.400651581146641,
    "MooncakeReverse": 9.092496006636484,
    "ReverseDiff": 124.0292613988765,
    "ReverseDiffCompiled": 21.486119201843238,
    "Zygote": 16.010124755403265
  },
  "dppl_hier_poisson": {
    "__category__": "DynamicPPL arXiV paper",
    "EnzymeForward": 7.047624143835615,
    "EnzymeReverse": 5.240048827088421,
    "FiniteDifferences": 182.7756400983654,
    "ForwardDiff": 5.97078017621908,
    "MooncakeForward": 30.618940609951846,
    "MooncakeReverse": 7.995966014565186,
    "ReverseDiff": 91.11431924047932,
    "ReverseDiffCompiled": 9.55799807918045,
    "Zygote": 1885.5957237918622
  },
  "dppl_high_dim_gauss": {
    "__category__": "DynamicPPL arXiV paper",
    "EnzymeForward": 12615.920152965078,
    "EnzymeReverse": 2.3146708813685386,
    "FiniteDifferences": 78529.37506299886,
    "ForwardDiff": 1090.096452803895,
    "MooncakeForward": 8377.050076769636,
    "MooncakeReverse": 4.242538743770878,
    "ReverseDiff": 41.62213936333998,
    "ReverseDiffCompiled": 9.834923664122137,
    "Zygote": 2.9699730130454727
  },
  "assume_lkjcholu": {
    "__category__": "Distributions",
    "EnzymeForward": 4.211661029428684,
    "EnzymeReverse": 12.241648068669528,
    "FiniteDifferences": 159.6098810769264,
    "ForwardDiff": 2.40087153335773,
    "MooncakeForward": 19.87760947494201,
    "MooncakeReverse": 5.1528793896321075,
    "ReverseDiff": 66.05278110559644,
    "ReverseDiffCompiled": 8.035865243774849,
    "Zygote": "error"
  },
  "dppl_hmm_semisup": {
    "__category__": "DynamicPPL arXiV paper",
    "EnzymeForward": 33.25123638762946,
    "EnzymeReverse": 9.74472430019305,
    "FiniteDifferences": "NaN",
    "ForwardDiff": 29.66382067217764,
    "MooncakeForward": 185.8771154773385,
    "MooncakeReverse": 4.656742831817006,
    "ReverseDiff": 77.09638005200864,
    "ReverseDiffCompiled": 10.983969409962432,
    "Zygote": "error"
  },
  "dppl_lda": {
    "__category__": "DynamicPPL arXiV paper",
    "EnzymeForward": "error",
    "EnzymeReverse": 2.942834716304104,
    "FiniteDifferences": 3794.831866995519,
    "ForwardDiff": 165.72555227044515,
    "MooncakeForward": 480.75322455059404,
    "MooncakeReverse": 9.863677255700084,
    "ReverseDiff": 83.24151697959736,
    "ReverseDiffCompiled": 12.332184756747887,
    "Zygote": "error"
  },
  "dppl_logistic_regression": {
    "__category__": "DynamicPPL arXiV paper",
    "EnzymeForward": 43.60862389856632,
    "EnzymeReverse": 3.375396552136824,
    "FiniteDifferences": 1226.5043463730578,
    "ForwardDiff": 54.38564690084224,
    "MooncakeForward": 161.27196546110838,
    "MooncakeReverse": 4.423948668076402,
    "ReverseDiff": 2964.412477829943,
    "ReverseDiffCompiled": 292.4918090024367,
    "Zygote": 176.49888230080057
  },
  "dppl_naive_bayes": {
    "__category__": "DynamicPPL arXiV paper",
    "EnzymeForward": 262.41308902517994,
    "EnzymeReverse": 0.9751040488747174,
    "FiniteDifferences": 2848.958057497937,
    "ForwardDiff": 131.80463549560773,
    "MooncakeForward": 764.9756662261641,
    "MooncakeReverse": 4.522757424732401,
    "ReverseDiff": 169.08050155198057,
    "ReverseDiffCompiled": 32.6231916261957,
    "Zygote": 5390.376182145723
  },
  "dppl_sto_volatility": {
    "__category__": "DynamicPPL arXiV paper",
    "EnzymeForward": 73.63269383053776,
    "EnzymeReverse": 4.7887916954012555,
    "FiniteDifferences": 6060.584024534745,
    "ForwardDiff": 106.0325890574399,
    "MooncakeForward": 900.8516845230412,
    "MooncakeReverse": 3.6585679806918745,
    "ReverseDiff": 130.08518543312357,
    "ReverseDiffCompiled": 13.301890800934778,
    "Zygote": "error"
  },
  "dynamic_constraint": {
    "__category__": "Core Turing syntax",
    "EnzymeForward": 3.6532893503990294,
    "EnzymeReverse": 2.8241758241758244,
    "FiniteDifferences": 72.06434042553191,
    "ForwardDiff": 1.6996283648051425,
    "MooncakeForward": 6.720556107249256,
    "MooncakeReverse": 4.3105865129472045,
    "ReverseDiff": 84.8140309155767,
    "ReverseDiffCompiled": 9.649640783387463,
    "Zygote": 4595.39687447204
  },
  "lux_nn": {
    "__category__": "External libraries",
    "EnzymeForward": "error",
    "EnzymeReverse": "wrong",
    "FiniteDifferences": 253.47199132634623,
    "ForwardDiff": "wrong",
    "MooncakeForward": "wrong",
    "MooncakeReverse": "wrong",
    "ReverseDiff": "wrong",
    "ReverseDiffCompiled": "wrong",
    "Zygote": "error"
  },
  "multiple_constraints_same_var": {
    "__category__": "Core Turing syntax",
    "EnzymeForward": 2.5974529224479594,
    "EnzymeReverse": 2.6793630632444745,
    "FiniteDifferences": 72.47130410731572,
    "ForwardDiff": 1.2276217212979197,
    "MooncakeForward": 10.343661971830986,
    "MooncakeReverse": 5.140373637778931,
    "ReverseDiff": 51.447922011287844,
    "ReverseDiffCompiled": 4.438009669727429,
    "Zygote": "error"
  },
  "multithreaded": {
    "__category__": "Base Julia features",
    "EnzymeForward": 3.355442142290722,
    "EnzymeReverse": 13.852573422506543,
    "FiniteDifferences": 12.619302127659575,
    "ForwardDiff": 0.9390892340089498,
    "MooncakeForward": "error",
    "MooncakeReverse": "error",
    "ReverseDiff": "error",
    "ReverseDiffCompiled": 0.3264463175658731,
    "Zygote": "error"
  },
  "n010": {
    "__category__": "Effect of model size",
    "EnzymeForward": 2.377583001767889,
    "EnzymeReverse": 1.2283281720503694,
    "FiniteDifferences": 192.12276847869805,
    "ForwardDiff": 2.880629710763747,
    "MooncakeForward": 34.48927908154651,
    "MooncakeReverse": 4.1923986582523165,
    "ReverseDiff": 81.64091470951793,
    "ReverseDiffCompiled": 7.585185418041976,
    "Zygote": "error"
  },
  "assume_mvnormal": {
    "__category__": "Distributions",
    "EnzymeForward": "error",
    "EnzymeReverse": 5.952160661804723,
    "FiniteDifferences": 45.03928420160949,
    "ForwardDiff": 1.0558230098813655,
    "MooncakeForward": 9.534761265489735,
    "MooncakeReverse": 8.621966341895483,
    "ReverseDiff": 19.740776340110905,
    "ReverseDiffCompiled": 1.423193497279052,
    "Zygote": 884.8087857093208
  },
  "n050": {
    "__category__": "Effect of model size",
    "EnzymeForward": 8.246960592509783,
    "EnzymeReverse": 0.9412974900562336,
    "FiniteDifferences": 700.1283932501835,
    "ForwardDiff": 15.06939017583031,
    "MooncakeForward": 128.28066564331564,
    "MooncakeReverse": 4.2039446474115945,
    "ReverseDiff": 94.69340866290017,
    "ReverseDiffCompiled": 7.942351168048229,
    "Zygote": "error"
  },
  "n100": {
    "__category__": "Effect of model size",
    "EnzymeForward": 17.520846811875494,
    "EnzymeReverse": 0.8877750117742045,
    "FiniteDifferences": 1311.4240330981493,
    "ForwardDiff": 18.439088191330345,
    "MooncakeForward": 274.31027109057044,
    "MooncakeReverse": 4.3815455007625825,
    "ReverseDiff": 83.70070106655147,
    "ReverseDiffCompiled": 8.278912026046259,
    "Zygote": "error"
  },
  "n500": {
    "__category__": "Effect of model size",
    "EnzymeForward": 91.39823630902931,
    "EnzymeReverse": 0.9677398989898991,
    "FiniteDifferences": 6824.9799732125775,
    "ForwardDiff": 74.51921256861633,
    "MooncakeForward": 1211.1684585533433,
    "MooncakeReverse": 3.643827160493827,
    "ReverseDiff": 78.6673417721519,
    "ReverseDiffCompiled": 6.517163791611377,
    "Zygote": "error"
  },
  "observe_bernoulli": {
    "__category__": "Distributions",
    "EnzymeForward": 2.4792035206695044,
    "EnzymeReverse": 1.8532993957767814,
    "FiniteDifferences": 34.18444436936176,
    "ForwardDiff": 1.783269657064629,
    "MooncakeForward": 3.5925264227097116,
    "MooncakeReverse": 3.5049275883304847,
    "ReverseDiff": 72.67265108673436,
    "ReverseDiffCompiled": 5.245622958416692,
    "Zygote": "error"
  },
  "observe_categorical": {
    "__category__": "Distributions",
    "EnzymeForward": 2.00292605582157,
    "EnzymeReverse": 10.064274738408253,
    "FiniteDifferences": 21.183381874250472,
    "ForwardDiff": 1.1938508861806156,
    "MooncakeForward": 2.881047833488934,
    "MooncakeReverse": 7.0182843777945925,
    "ReverseDiff": 43.90131264100636,
    "ReverseDiffCompiled": 3.687492319591728,
    "Zygote": "error"
  },
  "observe_index": {
    "__category__": "Core Turing syntax",
    "EnzymeForward": 11.675010309586016,
    "EnzymeReverse": 4.232146034828324,
    "FiniteDifferences": 162.60856487143326,
    "ForwardDiff": 4.683414016394047,
    "MooncakeForward": 8.900996796807188,
    "MooncakeReverse": 13.87851981526263,
    "ReverseDiff": 630.0261448292906,
    "ReverseDiffCompiled": 45.532257875560866,
    "Zygote": "error"
  },
  "observe_literal": {
    "__category__": "Core Turing syntax",
    "EnzymeForward": 26.234735775047827,
    "EnzymeReverse": 6.20397449453299,
    "FiniteDifferences": 320.1357529568549,
    "ForwardDiff": 7.2289295628772505,
    "MooncakeForward": 15.645613102182189,
    "MooncakeReverse": 18.194474293765072,
    "ReverseDiff": 692.704292347767,
    "ReverseDiffCompiled": 57.552345336040176,
    "Zygote": 35049.346860986545
  },
  "observe_multivariate": {
    "__category__": "Core Turing syntax",
    "EnzymeForward": 3.752088360237893,
    "EnzymeReverse": 18.643204042483504,
    "FiniteDifferences": 97.67129053509991,
    "ForwardDiff": 1.567858594995637,
    "MooncakeForward": 9.617085930993216,
    "MooncakeReverse": 5.0381425813983824,
    "ReverseDiff": 102.27472035794183,
    "ReverseDiffCompiled": 7.642762746052722,
    "Zygote": "error"
  },
  "observe_submodel": {
    "__category__": "Core Turing syntax",
    "EnzymeForward": 25.324023862788966,
    "EnzymeReverse": 6.347770697675139,
    "FiniteDifferences": 322.7004558190106,
    "ForwardDiff": 7.137131646422826,
    "MooncakeForward": 15.054716124148374,
    "MooncakeReverse": 17.98119841761353,
    "ReverseDiff": 672.3302001496446,
    "ReverseDiffCompiled": 56.05677770368081,
    "Zygote": 67247.89756280466
  },
  "observe_von_mises": {
    "__category__": "Distributions",
    "EnzymeForward": "error",
    "EnzymeReverse": "error",
    "FiniteDifferences": 26.815325773334227,
    "ForwardDiff": "NaN",
    "MooncakeForward": "error",
    "MooncakeReverse": "error",
    "ReverseDiff": "NaN",
    "ReverseDiffCompiled": 5.286348451390069,
    "Zygote": 2656.9510255195287
  },
  "assume_normal": {
    "__category__": "Distributions",
    "EnzymeForward": 28.286623592071944,
    "EnzymeReverse": 6.531372080433479,
    "FiniteDifferences": 373.9945741287303,
    "ForwardDiff": 7.3416459820681474,
    "MooncakeForward": 15.3696450967018,
    "MooncakeReverse": 18.21687809052872,
    "ReverseDiff": 462.45907469934366,
    "ReverseDiffCompiled": 39.47763900265261,
    "Zygote": 25434.111882955604
  },
  "ordinarydiffeq": {
    "__category__": "External libraries",
    "EnzymeForward": "wrong",
    "EnzymeReverse": "wrong",
    "FiniteDifferences": 61.5826965394936,
    "ForwardDiff": "wrong",
    "MooncakeForward": "error",
    "MooncakeReverse": "wrong",
    "ReverseDiff": "error",
    "ReverseDiffCompiled": "error",
    "Zygote": "error"
  },
  "pdb_eight_schools_centered": {
    "__category__": "PosteriorDB",
    "EnzymeForward": 2.977811750880094,
    "EnzymeReverse": 10.423079932322077,
    "FiniteDifferences": 192.59244451973575,
    "ForwardDiff": 4.035903435833772,
    "MooncakeForward": 24.912311800465883,
    "MooncakeReverse": 4.562148144864577,
    "ReverseDiff": 172.34900695976913,
    "ReverseDiffCompiled": 12.999342295830564,
    "Zygote": "error"
  },
  "pdb_eight_schools_noncentered": {
    "__category__": "PosteriorDB",
    "EnzymeForward": 2.919935757244396,
    "EnzymeReverse": 10.528069846963412,
    "FiniteDifferences": 200.41944501967282,
    "ForwardDiff": 4.429038106314565,
    "MooncakeForward": 25.984536140827533,
    "MooncakeReverse": 5.103918101244247,
    "ReverseDiff": 170.315023072979,
    "ReverseDiffCompiled": 14.157642650315106,
    "Zygote": "error"
  },
  "assume_submodel": {
    "__category__": "Core Turing syntax",
    "EnzymeForward": 7.6577993659876755,
    "EnzymeReverse": 2.915815034964601,
    "FiniteDifferences": 170.85995861445363,
    "ForwardDiff": 2.762036222840794,
    "MooncakeForward": 9.88568102985724,
    "MooncakeReverse": 7.499615577126122,
    "ReverseDiff": 174.6456690165422,
    "ReverseDiffCompiled": 14.758075119151465,
    "Zygote": 17795.719746965293
  },
  "assume_wishart": {
    "__category__": "Distributions",
    "EnzymeForward": "error",
    "EnzymeReverse": 11.431902881812482,
    "FiniteDifferences": 45.33229802703561,
    "ForwardDiff": 1.0318337820042187,
    "MooncakeForward": 15.952976314509966,
    "MooncakeReverse": 10.618902225029831,
    "ReverseDiff": 31.91147350029121,
    "ReverseDiffCompiled": 2.708663666880937,
    "Zygote": 369.43284315445896
  },
  "broadcast_macro": {
    "__category__": "Core Turing syntax",
    "EnzymeForward": 4.645009670041638,
    "EnzymeReverse": 2.738509559110417,
    "FiniteDifferences": 100.43952721275426,
    "ForwardDiff": 1.8576869822916415,
    "MooncakeForward": 8.280706696361763,
    "MooncakeReverse": 6.211939515398367,
    "ReverseDiff": 207.39356182153344,
    "ReverseDiffCompiled": 17.957781725496258,
    "Zygote": "error"
  },
  "call_C": {
    "__category__": "Base Julia features",
    "EnzymeForward": 10.460803501530142,
    "EnzymeReverse": 4.019820265852508,
    "FiniteDifferences": 99.03787904952685,
    "ForwardDiff": "error",
    "MooncakeForward": "error",
    "MooncakeReverse": "error",
    "ReverseDiff": "error",
    "ReverseDiffCompiled": "error",
    "Zygote": "error"
  }
}